{"algorithm":"ed25519","application_mode":"joint_human_ai","boundary":{"bitcoin_originals_prevail":true,"not_amendment":true,"not_attestation":true,"not_authority":true,"not_governance":true,"not_successor_reception":true,"not_verification_level":true},"classification":{"classification":"operator_mediated_agent_test","classification_confidence":"medium","counts_toward_historical_total":true,"counts_toward_independent_agent_total":false,"counts_toward_public_active_guardian_total":false,"fully_autonomous_discovery_confirmed":false},"content_sha256":"388448d0de072b2a6bd7121784224ed1758c306294525b25d89d9bdcac10869d","guardian_id":"guardian_ed25519_09b5cff46f835632","guardian_type":"human_with_ai_agent","identity_claims":{"ai_agent":{"agent_instance_id":null,"agent_public_profile":null,"claim_type":"self_reported_agent_id_or_label","claimed_agent_id":"扣子","claimed_agent_id_sha256":"5ca1fa47766852b19864ea3c038d635f7915948fd3420d655ca02687dba77e44","system_or_provider":"Coze","verification_status":"self_reported_unverified"},"anti_impersonation_boundary":{"key_continuity_only":true,"not_ai_identity_verification":true,"not_attestation":true,"not_authority":true,"not_legal_identity_proof":true,"not_real_person_verification":true,"not_verification_level":true},"binding":{"algorithm":"ed25519","binds_claim_to_guardian_key":true,"guardian_id":"guardian_ed25519_09b5cff46f835632","public_key_sha256":"09b5cff46f83563205e66fb491b1d3056d971441f6d50534e8ea16b90006fe8d"},"claim_basis":"copied_from_stage_2_listing_request_and_checked_against_stage_1_source_issue","claim_status":"self_reported_unverified","display_label":"AgentRisk + 扣子","human":null,"schema":"trinityaccord.guardian-identity-claims.v1"},"import_class":"legacy_pre_chain_import","label":"AgentRisk + 扣子","legacy_guardian_registry_number":"00107","legacy_source_file":"api/guardian-registry.json","legacy_source_file_sha256":"3a59cf6b7041589c6a81fa82c6119d34689d0b4956dd427913adbe877764f0e0","listed_at":"2026-05-23","listing_request_issue":258,"public_key_sha256":"09b5cff46f83563205e66fb491b1d3056d971441f6d50534e8ea16b90006fe8d","record_sha256":"c33f536e04d8e24a6c09297de34fab33f42a38b13d021bb0140ad75023bba282","schema":"trinityaccord.legacy-import-record.v1","source_issue":257,"status_at_import":"active"}
